crPrint.py
setup.py
crPrint.egg-info/PKG-INFO
crPrint.egg-info/SOURCES.txt
crPrint.egg-info/dependency_links.txt
crPrint.egg-info/top_level.txt