Metadata-Version: 1.1
Name: crPrint
Version: 0.3
Summary: Print text with color
Home-page: https://twitter.com/joaok63
Author: João Mário
Author-email: joaok63@outlook.com
License: GPLv3
Keywords: color colour print console
Platform: UNKNOWN
Classifier: Development Status :: 3 - Alpha
Classifier: Environment :: Console
Classifier: Programming Language :: Python :: 3
Classifier: Programming Language :: Python :: 3.3
Classifier: Programming Language :: Python :: 3.4
Classifier: Programming Language :: Python :: 3.5
